pookie/__init__.py
pookie/cli.py
pookie/config.py
pookie/executor.py
pookie/gemini_api.py
pookie/utils.py
pookie_ai-1.0.1.dist-info/licenses/LICENSE
pookie_ai-1.0.1.dist-info/METADATA
pookie_ai-1.0.1.dist-info/WHEEL
pookie_ai-1.0.1.dist-info/entry_points.txt
pookie_ai-1.0.1.dist-info/top_level.txt
pookie_ai-1.0.1.dist-info/RECORD
